Phase-1/RegMem.v
`timescale 1ns/1ps

module RegMem(
    input clk,reset,
    input [4:0] read_reg1,read_reg2,write_reg,
    input [63:0] write_data,
    input reg_write_en,
    output [63:0] read_data1,read_data2);
    reg [63:0] registers [0:31];
    integer i;
    always @(posedge clk or posedge reset) begin
        if (reset) begin
            for (i = 0; i < 32; i = i + 1)
                registers[i] <= 64'b0;
        end else if (reg_write_en && write_reg != 5'b00000) begin
            registers[write_reg] <= write_data;
        end
    end
    assign read_data1 = (read_reg1 == 5'b00000) ? 64'b0 : registers[read_reg1];
    assign read_data2 = (read_reg2 == 5'b00000) ? 64'b0 : registers[read_reg2];
    task dump_registers;
        input integer cycle_count;
        integer file_handle;
        integer j;
        begin
            file_handle = $fopen("register_file.txt", "w");
            for (j = 0; j < 32; j = j + 1) begin
                $fwrite(file_handle, "%016h\n", registers[j]);
            end
            $fwrite(file_handle, "%0d\n", cycle_count);
            $fclose(file_handle);
        end
    endtask

endmodule

Phase-1/RegMem_tb.v
`timescale 1ns/1ps
`include "RegMem.v"

module RegMem_tb;
    reg clk, reset;
    reg [4:0] read_reg1, read_reg2, write_reg;
    reg [63:0] write_data;
    reg reg_write_en;
    wire [63:0] read_data1, read_data2;
    RegMem uut (
        .clk(clk),
        .reset(reset),
        .read_reg1(read_reg1),.read_reg2(read_reg2),.write_reg(write_reg),
        .write_data(write_data),
        .reg_write_en(reg_write_en),
        .read_data1(read_data1),.read_data2(read_data2));
    initial clk = 0;
    always #5 clk = ~clk;
    initial begin
        $dumpfile("RegMem_tb.vcd");
        $dumpvars(0, RegMem_tb);
        
        reset = 1;
        reg_write_en = 0;
        read_reg1 = 0;
        read_reg2 = 0;
        write_reg = 0;
        write_data = 0;
        #10;
        reset = 0;
        read_reg1 = 5'd1;
        #1;
        $display("RESET TEST: x1 = %h (expected 0)", read_data1);

        @(posedge clk);
        reg_write_en = 1;
        write_reg = 5'd1;
        write_data = 64'hDEAD_BEEF_CAFE_BABE;

        @(posedge clk);
        reg_write_en = 0;
        read_reg1 = 5'd1;
        read_reg2 = 5'd0;
        #1;
        $display("WRITE TEST: x1 = %h (expected DEAD_BEEF_CAFE_BABE)", read_data1);
        $display("WRITE TEST: x0 = %h (expected 0)", read_data2);

        @(posedge clk);
        reg_write_en = 1;
        write_reg = 5'd0;
        write_data = 64'hFFFF_FFFF_FFFF_FFFF;

        @(posedge clk);
        reg_write_en = 0;
        read_reg1 = 5'd0;
        #1;
        $display("x0 TEST: x0 = %h (expected 0)", read_data1);

        @(posedge clk);
        reg_write_en = 1; write_reg = 5'd2; write_data = 64'd10;
        @(posedge clk);
        write_reg = 5'd3; write_data = 64'd20;
        @(posedge clk);
        reg_write_en = 0;

        read_reg1 = 5'd2;
        read_reg2 = 5'd3;
        #1;
        $display("MULTI WRITE: x2 = %d (expected 10)", read_data1);
        $display("MULTI WRITE: x3 = %d (expected 20)", read_data2);

        read_reg1 = 5'd3;
        read_reg2 = 5'd3;
        #1;
        $display("DUAL READ: x3 = %d , %d (expected 20,20)",read_data1, read_data2);
        reset = 1; #10; reset = 0;
        read_reg1 = 5'd1;
        read_reg2 = 5'd2;
        #1;
        $display("RESET AFTER WRITE: x1=%h x2=%h (expected 0,0)",read_data1, read_data2);

        @(posedge clk);
        reg_write_en = 1;
        write_reg = 5'd5;
        write_data = 64'h1234_5678_9ABC_DEF0;
        @(posedge clk);
        reg_write_en = 0;
        read_reg1 = 5'd5;
        #1;
        $display("POST RESET WRITE: x5=%h (expected 123456789ABCDEF0)",read_data1);

        uut.dump_registers(42);
        $display("register_file.txt dumped (cycle_count = 42)");
        $finish;
    end
endmodule

Phase-1/RegMem_tb.vcd
$date
	Sun Feb 22 14:12:57 2026
$end
$version
	Icarus Verilog
$end
$timescale
	1ps
$end
$scope module RegMem_tb $end
$var wire 64 ! read_data2 [63:0] $end
$var wire 64 " read_data1 [63:0] $end
$var reg 1 # clk $end
$var reg 5 $ read_reg1 [4:0] $end
$var reg 5 % read_reg2 [4:0] $end
$var reg 1 & reg_write_en $end
$var reg 1 ' reset $end
$var reg 64 ( write_data [63:0] $end
$var reg 5 ) write_reg [4:0] $end
$scope module uut $end
$var wire 1 # clk $end
$var wire 5 * read_reg1 [4:0] $end
$var wire 5 + read_reg2 [4:0] $end
$var wire 1 & reg_write_en $end
$var wire 1 ' reset $end
$var wire 64 , write_data [63:0] $end
$var wire 5 - write_reg [4:0] $end
$var wire 64 . read_data2 [63:0] $end
$var wire 64 / read_data1 [63:0] $end
$var integer 32 0 i [31:0] $end
$scope task dump_registers $end
$var integer 32 1 cycle_count [31:0] $end
$var integer 32 2 file_handle [31:0] $end
$var integer 32 3 j [31:0] $end
$upscope $end
$upscope $end
$upscope $end
$enddefinitions $end
$comment Show the parameter values. $end
$dumpall
$end
#0
$dumpvars
bx 3
bx 2
bx 1
b100000 0
b0 /
b0 .
b0 -
b0 ,
b0 +
b0 *
b0 )
b0 (
1'
0&
b0 %
b0 $
0#
b0 "
b0 !
$end
#5000
b100000 0
1#
#10000
0#
b1 $
b1 *
0'
#15000
b1101111010101101101111101110111111001010111111101011101010111110 "
b1101111010101101101111101110111111001010111111101011101010111110 /
b1101111010101101101111101110111111001010111111101011101010111110 (
b1101111010101101101111101110111111001010111111101011101010111110 ,
b1 )
b1 -
1&
1#
#20000
0#
#25000
0&
1#
#30000
0#
#35000
b1111111111111111111111111111111111111111111111111111111111111111 (
b1111111111111111111111111111111111111111111111111111111111111111 ,
b0 )
b0 -
1&
1#
#40000
0#
#45000
b0 "
b0 /
b0 $
b0 *
0&
1#
#50000
0#
#55000
b1010 (
b1010 ,
b10 )
b10 -
1&
1#
#60000
0#
#65000
b10100 (
b10100 ,
b11 )
b11 -
1#
#70000
0#
#75000
b10100 !
b10100 .
b1010 "
b1010 /
b11 %
b11 +
b10 $
b10 *
0&
1#
#76000
b10100 "
b10100 /
b11 $
b11 *
#77000
b0 "
b0 /
b0 !
b0 .
b100000 0
1'
#80000
0#
#85000
b100000 0
1#
#87000
b10 %
b10 +
b1 $
b1 *
0'
#90000
0#
#95000
b1001000110100010101100111100010011010101111001101111011110000 (
b1001000110100010101100111100010011010101111001101111011110000 ,
b101 )
b101 -
1&
1#
#100000
0#
#105000
b1001000110100010101100111100010011010101111001101111011110000 "
b1001000110100010101100111100010011010101111001101111011110000 /
b101 $
b101 *
0&
1#
#106000
b100000 3
b10000000000000000000000000000011 2
b101010 1
